vistudio/__init__.py
vistudio/datasource/__init__.py
vistudio/datasource/sharded_mongo_datasink.py
vistudio_datasource-1.0.0.dist-info/METADATA
vistudio_datasource-1.0.0.dist-info/WHEEL
vistudio_datasource-1.0.0.dist-info/top_level.txt
vistudio_datasource-1.0.0.dist-info/RECORD
