Metadata-Version: 2.1
Name: vistudio-datasource
Version: 1.0.0
Summary: sdk in python for vistudio datasource
Home-page: https://console.cloud.baidu-int.com/devops/icode/repos/baidu/bce-vistudio/vistudio-annotation/blob/master
License: UNKNOWN
Platform: UNKNOWN
Requires-Python: >=3.6
Requires-Dist: ray
